qsonic/__init__.py
qsonic/calibration.py
qsonic/catalog.py
qsonic/io.py
qsonic/masks.py
qsonic/mathtools.py
qsonic/mpi_utils.py
qsonic/picca_continuum.py
qsonic/spectrum.py
qsonic/continuum_models/__init__.py
qsonic/continuum_models/base_continuum_model.py
qsonic/continuum_models/input_continuum_model.py
qsonic/continuum_models/picca_continuum_model.py
qsonic/continuum_models/true_continuum_model.py
qsonic/scripts/qsonic_calib.py
qsonic/scripts/qsonic_coadd_deltas.py
qsonic/scripts/qsonic_fit.py
qsonic-1.1.4.dist-info/LICENSE
qsonic-1.1.4.dist-info/METADATA
qsonic-1.1.4.dist-info/WHEEL
qsonic-1.1.4.dist-info/entry_points.txt
qsonic-1.1.4.dist-info/top_level.txt
qsonic-1.1.4.dist-info/RECORD
