Metadata-Version: 2.1
Name: qsonic
Version: 1.1.4
Summary: Quasar continuum fitter for DESI
Author: Naim Goksel Karacayli
Author-email: ngokselk@gmail.com
License: MIT
Project-URL: Bug Reports, https://github.com/p-slash/qsonic/issues
Project-URL: Documentation, http://qsonic.readthedocs.io/
Project-URL: Source, https://github.com/p-slash/qsonic
Requires-Python: >=3.7
License-File: LICENSE
Requires-Dist: numpy ~=1.26.0
Requires-Dist: numba ~=0.58.1
Requires-Dist: scipy ~=1.12.0
Requires-Dist: astropy ~=6.0.0
Requires-Dist: healpy ~=1.16.0
Requires-Dist: fitsio ~=1.1.9
Requires-Dist: iminuit ~=2.18.0
Requires-Dist: mpi4py
Provides-Extra: dev
Requires-Dist: pytest ; extra == 'dev'
Requires-Dist: flake8 ; extra == 'dev'
Requires-Dist: bump2version ; extra == 'dev'
Provides-Extra: doc
Requires-Dist: sphinx ; extra == 'doc'
Requires-Dist: sphinx-argparse ; extra == 'doc'
Requires-Dist: sphinx-rtd-theme ; extra == 'doc'
Provides-Extra: pub
Requires-Dist: build ; extra == 'pub'
Requires-Dist: twine ; extra == 'pub'
